{
    "name": "S\u00f6ren",
    "location": "Trondheim",
    "img": "https://res.cloudinary.com/miles/image/upload/c_fill,f_auto,g_face:center,h_260,w_260/v1686563172/Soren1_q0xi2a.jpg",
    "href": "https://www.miles.no/ansatte/soren-krum/",
    "description": "S\u00f6ren er tysk og utdannet maskiningeni\u00f8r. Han har v\u00e6rt offiser i det tyske milit\u00e6ret, og ble deretter introdusert til IT-verden, f\u00f8rst i Tyskland og deretter i Norge fra 2008.S\u00f6ren trives best i backend-systemene, og helst mellom forskjellige systemer som skal integreres med hverandre. Han har en st\u00f8dig bakgrunn fra IT-verden, med blant annet over 20 \u00e5rs erfaring fra Java.P\u00e5 fritiden finner du han p\u00e5 mange ulike steder: jernkledd p\u00e5 en middelaldermarket, eller i oljehyre p\u00e5 en gammal r\u00e5seiler, og om du sp\u00f8r pent, s\u00e5 viser han deg hvordan du vrir en vidiespenning. Om vinteren st\u00e5r han gjerne p\u00e5 ski, mest bortover, med mer iver enn talent.",
    "haiku": "Silicon engineer\nIntegrating worlds with ease\nWinter's snowy slope",
    "summary_en": "Here is a summary of the description of S\u00f6ren in English:\n\nS\u00f6ren is a German engineer with expertise in maskining and IT. He has a background as an officer in the German military before transitioning into the IT industry, first in Germany and then in Norway from 2008. In his free time, he enjoys various activities, including playing medieval dress-up and sailing, often showing off his skills to friends and family."
}