{
    "name": "Eivind",
    "location": "Bergen",
    "img": "https://res.cloudinary.com/miles/image/upload/c_fill,f_auto,g_face:center,h_260,w_260/v1675419707/Eivind_Web_gnfhil.jpg",
    "href": "https://www.miles.no/ansatte/eivind-lervik/",
    "description": "Eivind har en bachelor i dataingeni\u00f8r fra H\u00f8gskulen p\u00e5 Vestlandet, og har de siste 5 siste \u00e5rene jobbet som applikasjonsansvarlig. Det innebar rammeverksansvar for et in-house-rammeverk i bedriften, vedlikehold p\u00e5 applikasjoner p\u00e5 dette rammeverket, support og videreutvikling. Han har ogs\u00e5 hatt ansvar for flere IT-prosjekter der han b\u00e5de har hatt kontakt med intern-kunde, samt ledet utviklingen n\u00e5r prosjektene var i gang. Utenom dette er han daglig leder i eget enkeltpersonforetak. Eivind trives veldig godt n\u00e5r han jobber med konseptutforming, .NET/C#-programmering, relasjonsdatabaser, skytjenester og prosjektledelse.P\u00e5 fritiden spiller Eivind trommer i rockeband. Han er l\u00e5tskriver i bandet og har ansvaret for innspilling i eget lydstudio. Han lager musikkvideoer for bandet og trives godt med VFX-arbeid i Blender og DaVinci Resolve. I tillegg til musikken driver han med spillutvikling, fridykking, jakt og motorsport. Hvis tiden strekker til flyr han flysimulator og spiller dataspill. (Ogs\u00e5 brettspill som D&D).Eivind er veldig glad i \u00e5 teste nye aktiviteter!",
    "profession": "Utvikler",
    "haiku": "Data wizard reigns\nCoding, gaming, music born\nEivind's joy abounds",
    "summary_en": "Here is a summary of the description of Eivind in English:\n\nEivind has a bachelor's degree in data engineering from Vestlandet University and has worked as an application manager for the past 5 years, overseeing the maintenance and development of an in-house application framework. Outside of work, he leads his own solo business, spends time playing trombone in a rock band where he also produces music, creates music videos, and enjoys activities such as game development, hiking, hunting, motorsports, flying, and tabletop gaming like D&D. Eivind is enthusiastic about trying new things and has a diverse range of hobbies and interests."
}